[{"isPlaying": false, "users": [{"username": "radita", "isWinning": false, "isTurn": false, "isDefeated": false}], "gameRoomId": 1, "creator": "radita", "numPlayers": "2", "roomName": "Southern Ocean", "serverId": "2", "isEnded": false, "roomCreated": 1481675534, "size": "13"}, {"roomName": "Aegean Sea", "isEnded": false, "users": [{"username": "radita", "isWinning": false, "isTurn": false, "isDefeated": false}], "gameRoomId": 2, "creator": "radita", "roomCreated": 1481676009, "serverId": "2", "isPlaying": false, "numPlayers": "2", "size": "10"}]